{
    "name": "Alex Vega",
    "age": 35,
    "height": "5'9\"",
    "school": "University of Michigan",
    "job_industry": "Entertainment",
    "job_title": "Director",
    "hometown_location": "Miami, Florida",
    "dating_location": "Los Angeles, California",
    "languages_spoken": [
        "English",
        "Spanish"
    ],
    "values": "Family, Sustainability, Creativity",
    "interests": "Filmmaking, Basketball, Cooking, Traveling",
    "education_level": "Graduate",
    "religious_beliefs": "Agnostic",
    "politics": "Liberal",
    "dating_intentions": "Long term, open to short",
    "relationship_type": "Monogamy",
    "gender": "Non binary",
    "pronouns": "They/Them/Their",
    "sexuality": "Other",
    "ethnicity": "Hispanic/Latino",
    "has_children": false,
    "want_children": true,
    "pets": [
        "Cat"
    ],
    "zodiac_sign": "Leo",
    "mbti_personality_type": "ENFP",
    "drinking": "Sometimes",
    "smoking": "No",
    "marijuana": "No",
    "drugs": "No",
    "exercise": "Active",
    "partner_preferences": {
        "minimum_age": 28,
        "maximum_age": 40,
        "minimum_height": "5'0\"",
        "maximum_height": "6'0\"",
        "has_children": false,
        "want_children": true,
        "sexuality": "Other",
        "drinking": "No",
        "smoking": "No",
        "marijuana": "No",
        "drugs": "No",
        "exercise": "Active"
    },
    "summary": "Alex Vega, a 35-year-old non-binary Director working in the entertainment industry in Los Angeles, is seeking a long term relationship but is also open to short term. They are a graduate of the University of Michigan, identify as agnostic and liberal, and speak both English and Spanish. \n\nOriginally from Miami, Alex is of Hispanic/Latino ethnicity and prefers using \"they/them/their\" pronouns. They are an ENFP according to the Myers Briggs Type Indicator and their zodiac sign is Leo. While they do not have any children, they aspire to have them someday. Alex is active and occasionally enjoys a drink but does not consume smoking, marijuana, or any other drugs. In their free time, they indulge in activities like filmmaking, basketball, cooking, and traveling. Family bonds, sustainable living, and creativity are core parts of their personal values. \n\nAlex is interested in a partner aged between 28 and 40 years who is open to having children in the future. They prefer someone who is non-drinker, non-smoker, does not consume marijuana or engage in drug usage, and leads an active lifestyle. Alex is a cat lover and is hoping to find someone who shares the same penchant for pets.",
    "user_id": "40a47f27-1448-49e5-b2ef-8aabc11dce7b"
}
